{
  "generatedAt": "2026-06-27T22:28:08.316Z",
  "book": "nahj-al-balagha",
  "chapterPath": "/books/nahj-al-balagha:3:2",
  "chapter": {
    "path": "/books/nahj-al-balagha:3:2",
    "titles": {
      "en": "Charity as a cure and afterlife consequences"
    }
  },
  "count": 1,
  "records": [
    {
      "id": "nahj-al-balagha:3:2:1",
      "type": "hadith",
      "book": {
        "slug": "nahj-al-balagha",
        "titles": {
          "ar": "نهج البلاغة",
          "en": "Nahj al-Balagha"
        },
        "author": {
          "ar": "الشريف الرضي",
          "en": "Sharif al-Radi"
        }
      },
      "path": {
        "source": "/books/nahj-al-balagha:3:2:1",
        "parts": [
          3,
          2,
          1
        ]
      },
      "numbering": {
        "volume": 3,
        "book": 2,
        "chapter": 1
      },
      "chapter": {
        "path": "/books/nahj-al-balagha:3:2",
        "titles": {
          "en": "Charity as a cure and afterlife consequences"
        }
      },
      "arabic": {
        "segments": [
          "٧. وَقَالَ (عليه ‏السلام): الصَّدَقَةُ دَوَاءٌ مُنْجِحٌ، وَأَعْمَالُ الْعِبَادِ فِي عَاجِلِهِمْ، نُصْبُ أَعْيُنِهِمْ فِي آجِلِهِمْ."
        ],
        "text": "٧. وَقَالَ (عليه ‏السلام): الصَّدَقَةُ دَوَاءٌ مُنْجِحٌ، وَأَعْمَالُ الْعِبَادِ فِي عَاجِلِهِمْ، نُصْبُ أَعْيُنِهِمْ فِي آجِلِهِمْ."
      },
      "translations": {
        "en.sayed-ali-raza": {
          "segments": [
            "7. Amīr al-mu’minīn, peace be upon him, said: Charity is an effective cure, and the actions of people in their present life will be before their eyes in the next life. [1]"
          ],
          "text": "7. Amīr al-mu’minīn, peace be upon him, said: Charity is an effective cure, and the actions of people in their present life will be before their eyes in the next life. [1]"
        }
      },
      "gradings": [],
      "relations": {},
      "source": {
        "provider": "ThaqalaynData",
        "dataPath": "/books/nahj-al-balagha:3:2:1",
        "apiUrl": "file:///home/ali/shia-library-json/tmp/ThaqalaynData/books/nahj-al-balagha/3/2/1.json",
        "sourceUrl": "https://thaqalayn.net/hadith/32/3/7/8",
        "license": "CC0-1.0"
      }
    }
  ]
}
