{
  "id": 3465,
  "type": "narrator",
  "path": "/people/narrators/3465",
  "titles": {
    "ar": "عَبَّادِ بْنِ زِيَادٍ الْأَسَدِيِّ"
  },
  "versePaths": [
    "/books/al-kafi:5:3:151:3"
  ],
  "verseCount": 1,
  "relations": {},
  "subchains": {
    "1071-3465": {
      "narrator_ids": [
        1071,
        3465
      ],
      "verse_paths": [
        "/books/al-kafi:5:3:151:3"
      ]
    },
    "19-36-1071-3465-269-9-1691-145-278-669": {
      "narrator_ids": [
        19,
        36,
        1071,
        3465,
        269,
        9,
        1691,
        145,
        278,
        669
      ],
      "verse_paths": [
        "/books/al-kafi:5:3:151:3"
      ]
    },
    "3465-269": {
      "narrator_ids": [
        3465,
        269
      ],
      "verse_paths": [
        "/books/al-kafi:5:3:151:3"
      ]
    }
  },
  "source": {
    "provider": "ThaqalaynData",
    "baseUrl": "https://thaqalayndata.netlify.app",
    "localDir": "/home/ali/shia-library-json/tmp/ThaqalaynData",
    "license": "CC0-1.0",
    "dataPath": "/people/narrators/3465",
    "apiUrl": "file:///home/ali/shia-library-json/tmp/ThaqalaynData/people/narrators/3465.json"
  }
}
